deephub/__init__.py
deephub/__main__.py
deephub/common/__init__.py
deephub/common/const.py
deephub/common/gs_io.py
deephub/common/gsutil.py
deephub/common/io.py
deephub/common/logging.py
deephub/common/modules.py
deephub/common/utils.py
deephub/models/__init__.py
deephub/models/utils.py
deephub/models/feeders/__init__.py
deephub/models/feeders/base.py
deephub/models/feeders/memory.py
deephub/models/feeders/tfrecords/__init__.py
deephub/models/feeders/tfrecords/features.py
deephub/models/feeders/tfrecords/meta.py
deephub/models/registry/__init__.py
deephub/models/registry/toy.py
deephub/preprocessor/image/__init__.py
deephub/preprocessor/image/build_image_data.py
deephub/preprocessor/text/__init__.py
deephub/preprocessor/text/__main__.py
deephub/preprocessor/text/text_io.py
deephub/preprocessor/text/tokenizers.py
deephub/preprocessor/text/vocab.py
deephub/resources/__init__.py
deephub/resources/__main__.py
deephub/resources/remote.py
deephub/trainer/__init__.py
deephub/trainer/__main__.py
deephub/trainer/metrics.py
deephub/trainer/utils.py
deephub/utils/__init__.py
deephub/utils/__main__.py
deephub/variants/__init__.py
deephub/variants/definition.py
deephub/variants/io.py
deephub-0.9.1.dist-info/LICENSE
deephub-0.9.1.dist-info/METADATA
deephub-0.9.1.dist-info/WHEEL
deephub-0.9.1.dist-info/entry_points.txt
deephub-0.9.1.dist-info/top_level.txt
deephub-0.9.1.dist-info/RECORD
